odoo/addons/web_widget_product_label_section_and_note/README.rst
odoo/addons/web_widget_product_label_section_and_note/__init__.py
odoo/addons/web_widget_product_label_section_and_note/__manifest__.py
odoo/addons/web_widget_product_label_section_and_note/i18n/it.po
odoo/addons/web_widget_product_label_section_and_note/i18n/web_widget_product_label_section_and_note.pot
odoo/addons/web_widget_product_label_section_and_note/readme/CONFIGURE.md
odoo/addons/web_widget_product_label_section_and_note/readme/CONTRIBUTORS.md
odoo/addons/web_widget_product_label_section_and_note/readme/DESCRIPTION.md
odoo/addons/web_widget_product_label_section_and_note/readme/ROADMAP.md
odoo/addons/web_widget_product_label_section_and_note/readme/USAGE.md
odoo/addons/web_widget_product_label_section_and_note/static/description/icon.png
odoo/addons/web_widget_product_label_section_and_note/static/description/index.html
odoo/addons/web_widget_product_label_section_and_note/static/src/components/product_label_section_and_note_field/product_label_section_and_note_field.esm.js
odoo/addons/web_widget_product_label_section_and_note/static/src/components/product_label_section_and_note_field/product_label_section_and_note_field.scss
odoo/addons/web_widget_product_label_section_and_note/static/src/components/product_label_section_and_note_field/product_label_section_and_note_field.xml
odoo/addons/web_widget_product_label_section_and_note/static/src/core/utils/autoresize.esm.js
odoo/addons/web_widget_product_label_section_and_note/static/src/core/utils/product_and_label_autoresize.esm.js
odoo/addons/web_widget_product_label_section_and_note/views/account_move_views.xml
odoo_addon_web_widget_product_label_section_and_note-17.0.1.0.1.dist-info/METADATA
odoo_addon_web_widget_product_label_section_and_note-17.0.1.0.1.dist-info/WHEEL
odoo_addon_web_widget_product_label_section_and_note-17.0.1.0.1.dist-info/top_level.txt
odoo_addon_web_widget_product_label_section_and_note-17.0.1.0.1.dist-info/RECORD
