Metadata-Version: 2.1
Name: odoo-addon-web_widget_product_label_section_and_note
Version: 17.0.1.0.1
Requires-Python: >=3.10
Requires-Dist: odoo>=17.0a,<17.1dev
Summary: unify the product and name into a single column
Home-page: https://github.com/OCA/web
License: AGPL-3
Author: Tecnativa, Odoo Community Association (OCA), Odoo S.A.
Author-email: support@odoo-community.org
Classifier: Programming Language :: Python
Classifier: Framework :: Odoo
Classifier: Framework :: Odoo :: 17.0
Classifier: License :: OSI Approved :: GNU Affero General Public License v3
